bottomify-1.2.1.dist-info/METADATA
bottomify-1.2.1.dist-info/WHEEL
bottom/__init__.py
bottom/__init__.pyi
bottom/py.typed
bottom/bottom.cpython-38-x86_64-linux-gnu.so
bottomify-1.2.1.dist-info/RECORD
