Metadata-Version: 2.1
Name: bottomify
Version: 1.2.1
Classifier: License :: OSI Approved :: MIT License
Classifier: Development Status :: 5 - Production/Stable
Classifier: Intended Audience :: Developers
Classifier: Programming Language :: Python
Classifier: Programming Language :: Rust
Classifier: Typing :: Typed
Author: uYert Developers <bottom@josh-is.gay>
Author-email: uYert Developers <bottom@josh-is.gay>
